dmario24_plus/__init__.py
dmario24_plus/cal.py
dmario24_plus-0.1.0.dist-info/METADATA
dmario24_plus-0.1.0.dist-info/WHEEL
dmario24_plus-0.1.0.dist-info/top_level.txt
dmario24_plus-0.1.0.dist-info/RECORD
