Metadata-Version: 2.1
Name: dmario24_plus
Version: 0.1.0
Summary: Add two integers
Author-email: dMario24 <data.mario24@gmail.com>
License: MIT
Project-URL: Homepage, https://github.com/dMario24/dmario24_plus
Project-URL: Issues, https://github.com/dMario24/dmario24_plus/issues
Requires-Python: >=3.9
